voiladata/__init__.py
voiladata/main.py
voiladata-1.0.4.dist-info/licenses/LICENSE
voiladata-1.0.4.dist-info/METADATA
voiladata-1.0.4.dist-info/WHEEL
voiladata-1.0.4.dist-info/top_level.txt
voiladata-1.0.4.dist-info/RECORD
