Metadata-Version: 2.4
Name: voiladata
Version: 1.0.4
Summary: A versatile Python library to read various file formats into a pandas DataFrame, and perform basic data health checks.
Home-page: https://github.com/Dmukherjeetextiles/VoilaData
Author: Debrup Mukherjee
Author-email: dmukherjeetextiles@gmail.com
Classifier: Programming Language :: Python :: 3
Classifier: License :: OSI Approved :: MIT License
Classifier: Operating System :: OS Independent
Classifier: Intended Audience :: Developers
Classifier: Intended Audience :: Science/Research
Classifier: Topic :: Software Development :: Libraries :: Python Modules
Classifier: Topic :: Scientific/Engineering :: Information Analysis
Requires-Python: >=3.8
License-File: LICENSE
Requires-Dist: pandas>=1.5.0
Requires-Dist: numpy>=1.20.0
Provides-Extra: excel
Requires-Dist: openpyxl; extra == "excel"
Provides-Extra: yaml
Requires-Dist: PyYAML; extra == "yaml"
Provides-Extra: toml
Requires-Dist: toml; extra == "toml"
Provides-Extra: html
Requires-Dist: lxml; extra == "html"
Provides-Extra: arrow
Requires-Dist: pyarrow; extra == "arrow"
Provides-Extra: spss
Requires-Dist: pyreadstat; extra == "spss"
Provides-Extra: all
Requires-Dist: openpyxl; extra == "all"
Requires-Dist: PyYAML; extra == "all"
Requires-Dist: toml; extra == "all"
Requires-Dist: lxml; extra == "all"
Requires-Dist: pyarrow; extra == "all"
Requires-Dist: pyreadstat; extra == "all"
Dynamic: author
Dynamic: author-email
Dynamic: classifier
Dynamic: description
Dynamic: description-content-type
Dynamic: home-page
Dynamic: license-file
Dynamic: provides-extra
Dynamic: requires-dist
Dynamic: requires-python
Dynamic: summary
